EOxServer-1.5.3.data/scripts/eoxserver-atpd.py
EOxServer-1.5.3.data/scripts/eoxserver-instance.py
EOxServer-1.5.3.data/scripts/eoxserver-preprocess.py
EOxServer-1.5.3.data/scripts/eoxserver-validate_xml.py
eoxserver/__init__.py
eoxserver/views.py
eoxserver/backends/__init__.py
eoxserver/backends/access.py
eoxserver/backends/admin.py
eoxserver/backends/cache.py
eoxserver/backends/component.py
eoxserver/backends/config.py
eoxserver/backends/interfaces.py
eoxserver/backends/middleware.py
eoxserver/backends/models.py
eoxserver/backends/storage_auths.py
eoxserver/backends/storages.py
eoxserver/backends/testbase.py
eoxserver/backends/tests.py
eoxserver/backends/util.py
eoxserver/backends/keystone/__init__.py
eoxserver/backends/keystone/storage_auth.py
eoxserver/backends/management/__init__.py
eoxserver/backends/management/commands/__init__.py
eoxserver/backends/management/commands/storage.py
eoxserver/backends/management/commands/storageauth.py
eoxserver/backends/migrations/0001_initial.py
eoxserver/backends/migrations/0002_storage_auth.py
eoxserver/backends/migrations/0003_nameblank.py
eoxserver/backends/migrations/0004_storage_streaming.py
eoxserver/backends/migrations/0005_alter_storage_id_alter_storageauth_id.py
eoxserver/backends/migrations/__init__.py
eoxserver/conf/default.conf
eoxserver/conf/defaultAttributeDictionary
eoxserver/conf/default_formats.conf
eoxserver/contrib/__init__.py
eoxserver/contrib/gdal.py
eoxserver/contrib/gdal_array.py
eoxserver/contrib/mapserver.py
eoxserver/contrib/ogr.py
eoxserver/contrib/osr.py
eoxserver/contrib/vrt.py
eoxserver/contrib/vsi.py
eoxserver/core/__init__.py
eoxserver/core/component.py
eoxserver/core/config.py
eoxserver/core/instance.py
eoxserver/core/management.py
eoxserver/core/models.py
eoxserver/core/tests.py
eoxserver/core/views.py
eoxserver/core/commands/__init__.py
eoxserver/core/commands/create_instance.py
eoxserver/core/decoders/__init__.py
eoxserver/core/decoders/base.py
eoxserver/core/decoders/config.py
EOxServer-1.5.3.dist-info/LICENSE
EOxServer-1.5.3.dist-info/METADATA
EOxServer-1.5.3.dist-info/WHEEL
EOxServer-1.5.3.dist-info/top_level.txt
EOxServer-1.5.3.dist-info/RECORD
