Metadata-Version: 2.1
Name: EOxServer
Version: 1.5.3
Summary: EOxServer is a server for Earth Observation (EO) data
Home-page: http://eoxserver.org/
Author: EOX IT Services GmbH
Author-email: office@eox.at
Maintainer: EOX IT Services GmbH
Maintainer-email: packages@eox.at
License: EOxServer Open License (MIT-style)
Keywords: Earth Observation,EO,OGC,WCS,WMS
Classifier: Development Status :: 5 - Production/Stable
Classifier: Environment :: Console
Classifier: Environment :: Web Environment
Classifier: Framework :: Django
Classifier: Intended Audience :: End Users/Desktop
Classifier: Intended Audience :: Other Audience
Classifier: Intended Audience :: System Administrators
Classifier: Intended Audience :: Science/Research
Classifier: License :: OSI Approved :: MIT License
Classifier: Natural Language :: English
Classifier: Operating System :: OS Independent
Classifier: Programming Language :: Python
Classifier: Programming Language :: Python :: 3.8
Classifier: Programming Language :: Python :: 3.9
Classifier: Programming Language :: Python :: 3.10
Classifier: Topic :: Database
Classifier: Topic :: Internet
Classifier: Topic :: Internet :: WWW/HTTP
Classifier: Topic :: Internet :: WWW/HTTP :: Dynamic Content
Classifier: Topic :: Multimedia :: Graphics
Classifier: Topic :: Scientific/Engineering :: GIS
Classifier: Topic :: Scientific/Engineering :: Information Analysis
Classifier: Topic :: Scientific/Engineering :: Visualization
License-File: LICENSE
Requires-Dist: django-model-utils <5.0.0
Requires-Dist: django-prometheus ==2.3.*
Requires-Dist: django ==5.2.*
Requires-Dist: gdal ==3.8.4
Requires-Dist: gunicorn ==23.0.*
Requires-Dist: jsonfield ==3.1.*
Requires-Dist: lxml ==5.4.*
Requires-Dist: mapscript ==8.0.*
Requires-Dist: matplotlib ==3.10.*
Requires-Dist: numpy <2.0.0
Requires-Dist: psycopg2 ==2.9.*
Requires-Dist: pycql ==0.0.8
Requires-Dist: pyows >=0.2.6
Requires-Dist: python-keystoneclient <6.0.0
Requires-Dist: python-swiftclient <5.0.0
Requires-Dist: zipstream ==1.1.*
Provides-Extra: dev
Requires-Dist: black ; extra == 'dev'
Requires-Dist: flake8 ; extra == 'dev'
Requires-Dist: mypy ; extra == 'dev'
Requires-Dist: scipy ; extra == 'dev'
Provides-Extra: docs
Requires-Dist: myst-parser ; extra == 'docs'
Requires-Dist: sphinx ; extra == 'docs'
Requires-Dist: sphinx-rtd-theme ; extra == 'docs'
